<?xml version="1.0" encoding="UTF-8"?>
<persistence version="2.1" xmlns="http://xmlns.jcp.org/xml/ns/persistence" xmlns:xsi="http://www.w3.org/2001/XMLSchema-instance" xsi:schemaLocation="http://xmlns.jcp.org/xml/ns/persistence http://xmlns.jcp.org/xml/ns/persistence/persistence_2_1.xsd">
	<persistence-unit name="SCBSystemEJB" transaction-type="JTA">
		<jta-data-source>java:jboss/datasources/phoenix_test</jta-data-source>
		<class>zw.co.posb.entity.AdGbBranch</class>
		<class>zw.co.posb.entity.AdGbCrncy</class>
		<class>zw.co.posb.entity.AdGbRsm</class>
		<class>zw.co.posb.entity.DpHistory</class>
		<class>zw.co.posb.entity.ReversalsTb</class>
		<class>zw.co.posb.entity.StanchartTb</class>
		<class>zw.co.posb.entity.TlItemCapture</class>
		<class>zw.co.posb.entity.TlJournal</class>
	</persistence-unit>
</persistence>
